tf2md/__init__.py
tf2md/markdown.py
tf2md/parser.py
tf2md-0.1.0.dist-info/entry_points.txt
tf2md-0.1.0.dist-info/WHEEL
tf2md-0.1.0.dist-info/METADATA
tf2md-0.1.0.dist-info/RECORD
