Metadata-Version: 2.1
Name: tf2md
Version: 0.1.0
Summary: 
Author: Karl Webster
Author-email: 19327709+ktasper@users.noreply.github.com
Requires-Python: >=3.8,<4.0
Classifier: Programming Language :: Python :: 3
Classifier: Programming Language :: Python :: 3.8
Classifier: Programming Language :: Python :: 3.9
Classifier: Programming Language :: Python :: 3.10
Classifier: Programming Language :: Python :: 3.11
Requires-Dist: click (>=8.1.3,<9.0.0)
Requires-Dist: logging (>=0.4.9.6,<0.5.0.0)
Requires-Dist: mdutils (>=1.4.0,<2.0.0)
Requires-Dist: python-hcl2 (>=4.3.0,<5.0.0)
